Pokemon_AMG/__init__.py
Pokemon_AMG/pokemon.csv
Pokemon_AMG/random_pokemon.py
Pokemon_AMG-1.0.0.dist-info/METADATA
Pokemon_AMG-1.0.0.dist-info/WHEEL
Pokemon_AMG-1.0.0.dist-info/top_level.txt
Pokemon_AMG-1.0.0.dist-info/RECORD
