Metadata-Version: 2.1
Name: Pokemon_AMG
Version: 1.0.0
Summary: Esta libreria contiene la facilidad de generar un pokemon aleatorio como una pokebola
Author: Alexis
Author-email: axelgoma11@gamil.com
Requires-Dist: pandas
